{"name":"(Spanish) Find Assistance - All the functionality of the FOA questionnaire","id":"stories/fullRegression/regressionChecklistSpanish.story;(Spanish) Find Assistance - All the functionality of the FOA questionnaire","testSteps":[{"number":1,"description":"Given I am on the Find Assistance Spanish page","duration":2853,"startTime":"2018-03-09T11:13:14.267-05:00[America/New_York]","result":"SUCCESS","precondition":false,"children":[{"number":2,"description":"Open page: /es/obtener-asistencia/encontrar-ayuda","duration":2082,"startTime":"2018-03-09T11:13:15.037-05:00[America/New_York]","result":"SUCCESS","precondition":false}]},{"number":3,"description":"When I fully complete the questionnaire","duration":11011,"startTime":"2018-03-09T11:13:17.120-05:00[America/New_York]","result":"SUCCESS","precondition":false,"children":[{"number":4,"description":"Complete questionnaire","duration":11011,"startTime":"2018-03-09T11:13:17.120-05:00[America/New_York]","result":"SUCCESS","precondition":false}]},{"number":5,"description":"Then I should be able to see all of the content in Spanish","duration":12596,"startTime":"2018-03-09T11:13:28.131-05:00[America/New_York]","result":"SUCCESS","precondition":false,"children":[{"number":6,"description":"Verify spanish FOA expanded content visible","duration":12594,"startTime":"2018-03-09T11:13:28.133-05:00[America/New_York]","result":"SUCCESS","precondition":false}]},{"number":7,"description":"When I click next","duration":91,"startTime":"2018-03-09T11:13:40.727-05:00[America/New_York]","result":"SUCCESS","precondition":false,"children":[{"number":8,"description":"Clicks next FOA","duration":89,"startTime":"2018-03-09T11:13:40.728-05:00[America/New_York]","result":"SUCCESS","precondition":false}]},{"number":9,"description":"Then the 3 accordions should have content visible","duration":341,"startTime":"2018-03-09T11:13:40.819-05:00[America/New_York]","result":"SUCCESS","precondition":false,"children":[{"number":10,"description":"Tests apply online accordions","duration":339,"startTime":"2018-03-09T11:13:40.820-05:00[America/New_York]","result":"SUCCESS","precondition":false}]},{"number":11,"description":"When I click apply now in Spanish","duration":3138,"startTime":"2018-03-09T11:13:41.160-05:00[America/New_York]","result":"SUCCESS","precondition":false,"children":[{"number":12,"description":"Clicks spanish apply online","duration":3136,"startTime":"2018-03-09T11:13:41.161-05:00[America/New_York]","result":"SUCCESS","precondition":false}]},{"number":13,"description":"Then the DAC page should load","duration":2118,"startTime":"2018-03-09T11:13:44.298-05:00[America/New_York]","result":"SUCCESS","precondition":false,"children":[{"number":14,"description":"Should see DAC","duration":2116,"startTime":"2018-03-09T11:13:44.299-05:00[America/New_York]","result":"SUCCESS","precondition":false}]}],"userStory":{"id":"regressionChecklistSpanish","storyName":"Regression checklist spanish","path":"stories/fullRegression/regressionChecklistSpanish.story","narrative":"In order to assert that the basic functionality of https://www.disasterassistance.gov/es/ is working\nAs a tester\nI want to run the daily regressions at least twice a day\n\nMeta:","type":"story"},"featureTag":{"name":"Full regression/Regression checklist spanish","type":"story"},"title":"(Spanish) Find Assistance - All the functionality of the FOA questionnaire","tags":[{"name":"Full regression/Regression checklist spanish","type":"story"},{"name":"Full regression","type":"feature"}],"startTime":"2018-03-09T11:13:14.265-05:00[America/New_York]","duration":32151,"projectKey":"","sessionId":"bc5677a739c6e8a20ee76201614a39eb","driver":"chrome","manual":false,"testSource":"JBehave","result":"SUCCESS"}