{"name":"(Spanish) Address Look-Up - Declared disasters","id":"stories/fullRegression/regressionChecklistSpanish.story;(Spanish) Address Look-Up - Declared disasters","testSteps":[{"number":1,"description":"Given I am on the declared disasters DAC page","duration":2335,"startTime":"2018-06-11T11:57:02-04:00[America/New_York]","screenshots":[{"screenshot":"135dd80b52e3d51d188b770d31909e1c536403668efb0d805714acbb6c56a192.png"}],"result":"SUCCESS","precondition":false,"children":[{"number":2,"description":"Open disaster DAC page","duration":791,"startTime":"2018-06-11T11:57:03.214-04:00[America/New_York]","screenshots":[{"screenshot":"135dd80b52e3d51d188b770d31909e1c536403668efb0d805714acbb6c56a192.png"}],"result":"SUCCESS","precondition":false}]},{"number":3,"description":"When I type the declared disaster into the address look-up bar from the Address Look-Up page in Spanish","duration":12750,"startTime":"2018-06-11T11:57:04.335-04:00[America/New_York]","screenshots":[{"screenshot":"fc7a7b3ff7126c5c2aae3baf7c578244bf9420424cd735bd4bb4fc9ca63acb69.png"}],"result":"SUCCESS","precondition":false,"children":[{"number":4,"description":"Declared disasters page spanish","duration":12396,"startTime":"2018-06-11T11:57:04.336-04:00[America/New_York]","screenshots":[{"screenshot":"fc7a7b3ff7126c5c2aae3baf7c578244bf9420424cd735bd4bb4fc9ca63acb69.png"}],"result":"SUCCESS","precondition":false}]},{"number":5,"description":"Then I should get the results for the given disaster","duration":750,"startTime":"2018-06-11T11:57:17.085-04:00[America/New_York]","screenshots":[{"screenshot":"fc7a7b3ff7126c5c2aae3baf7c578244bf9420424cd735bd4bb4fc9ca63acb69.png"}],"result":"SUCCESS","precondition":false,"children":[{"number":6,"description":"Disaster results","duration":387,"startTime":"2018-06-11T11:57:17.086-04:00[America/New_York]","screenshots":[{"screenshot":"fc7a7b3ff7126c5c2aae3baf7c578244bf9420424cd735bd4bb4fc9ca63acb69.png"}],"result":"SUCCESS","precondition":false}]}],"userStory":{"id":"regressionChecklistSpanish","storyName":"Regression checklist spanish","path":"stories/fullRegression/regressionChecklistSpanish.story","narrative":"In order to assert that the basic functionality of https://www.disasterassistance.gov/es/ is working\nAs a tester\nI want to run the daily regressions at least twice a day\n\nMeta:","type":"story"},"featureTag":{"name":"Full regression/Regression checklist spanish","type":"story"},"title":"(Spanish) Address Look-Up - Declared disasters","tags":[{"name":"Full regression/Regression checklist spanish","type":"story"},{"name":"Full regression","type":"feature"}],"startTime":"2018-06-11T11:57:01.998-04:00[America/New_York]","duration":15838,"projectKey":"","sessionId":"827ed2947de3c16679243026a8170ee7","driver":"chrome","manual":false,"testSource":"JBehave","result":"SUCCESS"}