{"name":"(Spanish) Homepage - Currently declared disasters - The declared states on the declared disaster map","id":"stories/fullRegression/regressionChecklistSpanish.story;(Spanish) Homepage - Currently declared disasters - The declared states on the declared disaster map","testSteps":[{"number":1,"description":"Given I am on the Spanish Disaster Assistance homepage","duration":2330,"startTime":"2018-02-21T11:53:04.734-05:00[America/New_York]","result":"SUCCESS","precondition":false,"children":[{"number":2,"description":"Open page: /es","duration":1518,"startTime":"2018-02-21T11:53:05.545-05:00[America/New_York]","result":"SUCCESS","precondition":false}]},{"number":3,"description":"When I am viewing the declared disaster map","duration":83,"startTime":"2018-02-21T11:53:07.064-05:00[America/New_York]","result":"SUCCESS","precondition":false,"children":[{"number":4,"description":"Check disaster map","duration":81,"startTime":"2018-02-21T11:53:07.065-05:00[America/New_York]","result":"SUCCESS","precondition":false}]},{"number":5,"description":"Then states with disasters should be clickable","duration":679,"startTime":"2018-02-21T11:53:07.147-05:00[America/New_York]","result":"SUCCESS","precondition":false,"children":[{"number":6,"description":"Check states","duration":677,"startTime":"2018-02-21T11:53:07.149-05:00[America/New_York]","result":"SUCCESS","precondition":false}]},{"number":7,"description":"Then I should be able to view the list of the declared states in Spanish","duration":64226,"startTime":"2018-02-21T11:53:07.826-05:00[America/New_York]","result":"SUCCESS","precondition":false,"children":[{"number":8,"description":"Check spanish disaster state","duration":64225,"startTime":"2018-02-21T11:53:07.827-05:00[America/New_York]","result":"SUCCESS","precondition":false}]}],"userStory":{"id":"regressionChecklistSpanish","storyName":"Regression checklist spanish","path":"stories/fullRegression/regressionChecklistSpanish.story","narrative":"In order to assert that the basic functionality of https://www.disasterassistance.gov/es/ is working\nAs a tester\nI want to run the daily regressions at least twice a day\n\nMeta:","type":"story"},"featureTag":{"name":"Full regression/Regression checklist spanish","type":"story"},"title":"(Spanish) Homepage - Currently declared disasters - The declared states on the declared disaster map","tags":[{"name":"Full regression/Regression checklist spanish","type":"story"},{"name":"Full regression","type":"feature"}],"startTime":"2018-02-21T11:53:04.733-05:00[America/New_York]","duration":67319,"projectKey":"","sessionId":"d3230ac30f04494d6aba33c29f75a8e0","driver":"chrome","manual":false,"testSource":"JBehave","result":"SUCCESS"}